c2dp/__init__.py
c2dp/aws/__init__.py
c2dp/aws/aws.py
c2dp/cleaner/__init__.py
c2dp/cleaner/clean_cook.py
c2dp/cleaner/clean_tyler.py
c2dp/docs/__init__.py
c2dp/docs/documentation.py
c2dp/parser/__init__.py
c2dp/parser/parse_cook.py
c2dp/parser/parse_tyler.py
c2dp/parser/parsing_utils.py
c2dp/parser/verify_parsing.py
c2dp/scraper/__init__.py
c2dp/scraper/processMetadata.py
c2dp/scraper/scrape_CourtView.py
c2dp/scraper/scrape_cook.py
c2dp/scraper/scrape_openAccess.py
c2dp/scraper/scrape_tyler_technologies.py
c2dp-0.0.3.dist-info/METADATA
c2dp-0.0.3.dist-info/WHEEL
c2dp-0.0.3.dist-info/top_level.txt
c2dp-0.0.3.dist-info/RECORD
