Metadata-Version: 2.1
Name: c2dp
Version: 0.0.3
Summary: a library for the civil court data project
Home-page: UNKNOWN
Author: Dan Bernstein
Author-email: danbernstein94@gmail.com
License: UNKNOWN
Platform: UNKNOWN
